LICENSE
MANIFEST.in
README.rst
setup.cfg
setup.py
djangorestframework_jwt_v4.egg-info/PKG-INFO
djangorestframework_jwt_v4.egg-info/SOURCES.txt
djangorestframework_jwt_v4.egg-info/dependency_links.txt
djangorestframework_jwt_v4.egg-info/requires.txt
djangorestframework_jwt_v4.egg-info/top_level.txt
rest_framework_jwt/__init__.py
rest_framework_jwt/authentication.py
rest_framework_jwt/compat.py
rest_framework_jwt/models.py
rest_framework_jwt/serializers.py
rest_framework_jwt/settings.py
rest_framework_jwt/test.py
rest_framework_jwt/utils.py
rest_framework_jwt/views.py
rest_framework_jwt/locale/en_US/LC_MESSAGES/django.po